hrin_msb.py
msb/__init__.py
msb/apis/__init__.py
msb/apis/api_view.py
msb/apis/api_viewset.py
msb/apis/constants.py
msb/apis/errors.py
msb/apis/exceptions.py
msb/apis/funcs.py
msb/auth/__init__.py
msb/auth/authenticators.py
msb/auth/constants.py
msb/auth/decorators.py
msb/auth/defaults.py
msb/auth/exceptions.py
msb/auth/permissions.py
msb/auth/results.py
msb/auth/serializers.py
msb/auth/session.py
msb/auth/token.py
msb/auth/users.py
msb/auth/validators.py
msb/cipher/__init__.py
msb/cipher/asymmetric_cipher.py
msb/cipher/cipher.py
msb/cipher/constants.py
msb/cipher/exceptions.py
msb/cipher/symmetric_cipher.py
msb/dataclasses/__init__.py
msb/dataclasses/_email.py
msb/dataclasses/_singleton.py
msb/dataclasses/_wrappers.py
msb/dataclasses/notification.py
msb/dataclasses/search_parameter.py
msb/datetime/__init__.py
msb/datetime/constants.py
msb/datetime/wrappers.py
msb/db/__init__.py
msb/db/config_model.py
msb/db/constants.py
msb/db/logging_models.py
msb/db/metafields.py
msb/db/model_fields.py
msb/db/models.py
msb/db/msb_model.py
msb/db/msb_model_manager.py
msb/db/routers.py
msb/devtools/__init__.py
msb/devtools/constants.py
msb/devtools/dataclasses.py
msb/devtools/django.py
msb/devtools/funcs.py
msb/devtools/tasks.py
msb/env/__init__.py
msb/env/config.py
msb/env/constants.py
msb/env/core.py
msb/env/exceptions.py
msb/env/loging.py
msb/env/settings.py
msb/exceptions/__init__.py
msb/exceptions/_exception.py
msb/exceptions/handlers.py
msb/files/__init__.py
msb/files/core.py
msb/files/csv.py
msb/files/dataclasses.py
msb/files/docx.py
msb/files/exceptions.py
msb/files/factory.py
msb/files/messages.py
msb/files/pdf.py
msb/http/__init__.py
msb/http/client.py
msb/http/constants.py
msb/http/dataclasses.py
msb/http/exceptions.py
msb/http/request.py
msb/http/response.py
msb/http/utils.py
msb/http/wrappers.py
msb/logging/__init__.py
msb/logging/config.py
msb/logging/constants.py
msb/logging/handlers.py
msb/services/__init__.py
msb/services/api_service.py
msb/services/exceptions.py
hrin_msb-1.0.1.dist-info/LICENSE
hrin_msb-1.0.1.dist-info/METADATA
hrin_msb-1.0.1.dist-info/WHEEL
hrin_msb-1.0.1.dist-info/RECORD
