Metadata-Version: 2.1
Name: hrin-msb
Version: 1.0.1
Summary: 
Author: Prakash Mishra
Author-email: prakash.mishra@intimetec.com
Requires-Python: >=3.10,<4.0
Classifier: Programming Language :: Python :: 3
Classifier: Programming Language :: Python :: 3.10
Classifier: Programming Language :: Python :: 3.11
Classifier: Programming Language :: Python :: 3.12
Requires-Dist: celery (>=5.2.7,<6.0.0)
Requires-Dist: cerberus (>=1.3.4,<2.0.0)
Requires-Dist: cffi (>=1.15.1,<2.0.0)
Requires-Dist: cryptography (>=38.0.3,<39.0.0)
Requires-Dist: django (>=4.1.3,<5.0.0)
Requires-Dist: django-celery-results (>=2.5.1,<3.0.0)
Requires-Dist: django-cors-headers (>=4.0.0,<5.0.0)
Requires-Dist: djangorestframework (>=3.14.0,<4.0.0)
Requires-Dist: djangorestframework-simplejwt (>=5.2.2,<6.0.0)
Requires-Dist: pandas (>=2.0.2,<3.0.0)
Requires-Dist: pdf2docx (>=0.5.6,<0.6.0)
Requires-Dist: python-dateutil (>=2.8.2,<3.0.0)
Requires-Dist: python-dotenv (>=0.21.0,<0.22.0)
Requires-Dist: requests (>=2.28.1,<3.0.0)
Requires-Dist: user-agents (>=2.2.0,<3.0.0)
Requires-Dist: xhtml2pdf (>=0.2.8,<0.3.0)
